docx_revisions/__init__.py
docx_revisions/_helpers.py
docx_revisions/document.py
docx_revisions/oxml.py
docx_revisions/paragraph.py
docx_revisions/revision.py
docx_revisions/run.py
docx_revisions-0.1.3.dist-info/METADATA
docx_revisions-0.1.3.dist-info/WHEEL
docx_revisions-0.1.3.dist-info/licenses/LICENSE
docx_revisions-0.1.3.dist-info/RECORD
