Metadata-Version: 2.4
Name: docx-revisions
Version: 0.1.3
Summary: Track changes (revisions) support for python-docx: read, write and manipulate <w:ins> and <w:del> elements
Project-URL: Homepage, https://github.com/balalofernandez/docx-revisions
Project-URL: Documentation, https://balalofernandez.github.io/docx-revisions
Project-URL: Repository, https://github.com/balalofernandez/docx-revisions
License: MIT
License-File: LICENSE
Requires-Python: >=3.10
Requires-Dist: lxml>=4.9.0
Requires-Dist: python-docx>=1.1.0
Provides-Extra: dev
Requires-Dist: mkdocs-material>=9.0; extra == 'dev'
Requires-Dist: mkdocstrings[python]>=0.24; extra == 'dev'
Requires-Dist: pytest>=7.0; extra == 'dev'
Requires-Dist: ruff>=0.1; extra == 'dev'
Provides-Extra: examples
Requires-Dist: pydantic-ai>=1.51.0; extra == 'examples'
